django_db_comments/__init__.py
django_db_comments/apps.py
django_db_comments/db_comments.py
django_db_comments-0.4.1.dist-info/DESCRIPTION.rst
django_db_comments-0.4.1.dist-info/METADATA
django_db_comments-0.4.1.dist-info/RECORD
django_db_comments-0.4.1.dist-info/WHEEL
django_db_comments-0.4.1.dist-info/metadata.json
django_db_comments-0.4.1.dist-info/top_level.txt
